{"name":"Allure Report","stats":{"total":164,"passed":85,"skipped":79},"status":"passed","duration":12489811,"createdAt":1780233662000,"plugin":"Awesome","newTests":[{"id":"73eaa13ad662416394a03e2bbcfeee50","name":"should handle the vibium package gracefully [DEV]","status":"passed","duration":3960},{"id":"7808d26d520295d9fc772f55ceb16674","name":"dependencyTest() [DEV]","status":"passed","duration":2},{"id":"5ba90bebc1d12830581b2f5f9fe1eb0c","name":"Applications Integration Tests › should edit an existing application [DEV]","status":"skipped","duration":1000},{"id":"11680d7e4162671246d403a1a6abfca1","name":"fromStringToCanonicalXML() [DEV]","status":"skipped","duration":2},{"id":"f6ec1709decb584f75c1c503c968479b","name":"HomePage › should load the home page [DEV]","status":"passed","duration":1322},{"id":"ab0c649f97e0167150a28c4ed0afe059","name":"wellmark(TestInfo) [DEV]","status":"skipped","duration":0},{"id":"7d07855834906d922e9ec3fe628cd481","name":"testGeneratorClassExists() [DEV]","status":"passed","duration":1},{"id":"1913de64000aba7c15ab966f459b9704","name":"Applications Integration Tests › should view application details [DEV]","status":"skipped","duration":1000},{"id":"6fed7e254bed52db036fba5906a64a37","name":"Applications Integration Tests › should navigate to applications from home page [DEV]","status":"skipped","duration":1000},{"id":"d2e7f2c4e25fd922ab96f8894a41eba0","name":"microsoft(TestInfo) [DEV]","status":"skipped","duration":0},{"id":"cf555151b47e6aca4e62aca23c5206d7","name":"fromListToMap() [DEV]","status":"passed","duration":4},{"id":"7cb1b2869b61b20def81601d4b24a646","name":"testApiMethod() [DEV]","status":"skipped","duration":0},{"id":"195587cce7fd80e7b18accd41dc281fb","name":"testSecretRetrieval() [DEV]","status":"passed","duration":5},{"id":"3811e33e57af50d1c088cc6bba1d0993","name":"addTestGeneric() [DEV]","status":"passed","duration":1},{"id":"d54dc88cab05264bda2eb7af815f2e7f","name":"vivit(TestInfo) [DEV]","status":"skipped","duration":0},{"id":"d433ba1400e12861939dfce7c3b04112","name":"fromNumberToLetterExcel() [DEV]","status":"passed","duration":462},{"id":"9c2c17a413af5483e7f01787c1a3cedd","name":"Applications Integration Tests › should create a new application [DEV]","status":"skipped","duration":1000},{"id":"5d36af00392c4e36fd4ab0b19be20faf","name":"united(TestInfo) [DEV]","status":"skipped","duration":0},{"id":"b1b400278d4dcb501f4b5964bcb1be1b","name":"formatPretty() [DEV]","status":"skipped","duration":1},{"id":"accae08df0361e03efcd1b4e478b2510","name":"testGeneratorIsPublic() [DEV]","status":"passed","duration":1},{"id":"5ae87cc6ca2ad4eb8056a7a26b903784","name":"core(TestInfo) [DEV]","status":"skipped","duration":0},{"id":"a85763be172f9ff6181815746a0ab369","name":"vivitCommutes(TestInfo) [DEV]","status":"skipped","duration":0},{"id":"ff507e6d50358420b601a5d42e200865","name":"testClassSetup01(TestInfo) [DEV]","status":"skipped","duration":0},{"id":"ded5a7d44f783f64f13de3d93725f4e2","name":"t002(TestInfo) [DEV]","status":"skipped","duration":4},{"id":"9d00d032c1e3bb7cd2f515dbff6bb048","name":"assertXMLEqualPass() [DEV]","status":"skipped","duration":2},{"id":"86744db7b084e79deab4d1888018a52c","name":"testXLSX() [DEV]","status":"passed","duration":2031},{"id":"311a471c0e42ce8f8c766974a24eb79c","name":"testMethod() [DEV]","status":"skipped","duration":0},{"id":"39023d271e83f23f729a8110d770b5b8","name":"mainTest() [DEV]","status":"skipped","duration":0},{"id":"7f38b96475f71f5dd7c917cd10201571","name":"tBoxOfficeLists(TestInfo) [DEV]","status":"skipped","duration":0},{"id":"043d9b4de90d0ca1a06b87e9bedbe920","name":"Companies Integration Tests › should load companies list page [DEV]","status":"skipped","duration":1000},{"id":"4a67c7b4cc91b7d9d4d3cc5c1776e025","name":"testClassSetup02(TestInfo) [DEV]","status":"skipped","duration":0},{"id":"c50a199065c4e52b7825bea312d20367","name":"convertDBToXML() [DEV]","status":"skipped","duration":0},{"id":"11a2f287ab559d982f5442b61a2d5a92","name":"Wizard Tests › test_companies - Click Companies Navigation, Add button, populate all fields, then Cancel [DEV]","status":"passed","duration":2922},{"id":"6b3f871dc52a05428e33f608779d93b2","name":"testBoxOfficeMojo07(TestInfo) [DEV]","status":"skipped","duration":0},{"id":"2a9121d2307ba0a270e83bcfcb11aaab","name":"testBoxOfficeMojo34(TestInfo) [DEV]","status":"skipped","duration":0},{"id":"7cfa4823d1dccd8234bae2476438aadd","name":"testCodeCreation() [DEV]","status":"skipped","duration":0},{"id":"290917afa47da178e6d7def3789e5815","name":"testGridConnection(TestInfo) [DEV]","status":"skipped","duration":0},{"id":"6d99139be7b2689048640b7bea651b6d","name":"dropbox(TestInfo) [DEV]","status":"skipped","duration":0},{"id":"40aff04926aaa7bf23f82f2b639d0da5","name":"testCompanyEnvironmentData() [DEV]","status":"skipped","duration":0},{"id":"6db3ea2f2a9ef6ffa80f0ae427b64515","name":"Applications Integration Tests › should handle empty applications list [DEV]","status":"skipped","duration":1000},{"id":"ec41698047006f42d7554be74763b69d","name":"testResponsiveBreakpoints [DEV]","status":"passed","duration":1477},{"id":"fe8b9c1003e189cddf1324ac66771f21","name":"iaDhs(TestInfo) [DEV]","status":"skipped","duration":0},{"id":"e97f0e0997acd438a3f79722d2407113","name":"mining(TestInfo) [DEV]","status":"skipped","duration":0},{"id":"0a5fe59dc37b9f0d1e69e3da85c39b1b","name":"getDatePlusMinusTestCase() [DEV]","status":"passed","duration":3},{"id":"52f91f8b05bff2d24715c9ad16f7ee3c","name":"everyoneSocial(TestInfo) [DEV]","status":"skipped","duration":0},{"id":"764d21d5f93566f71f750b92c511517b","name":"Wizard Tests › test_application - Click Applications Navigation, Add button, then Cancel [DEV]","status":"passed","duration":1836},{"id":"a5a4995c9ebe3416156ac12b6db5575b","name":"americanAirlines(TestInfo) [DEV]","status":"skipped","duration":0},{"id":"90e46f987ab60087823b01177609a446","name":"gtwWebinarServiceTest() [DEV]","status":"skipped","duration":0},{"id":"1d537afb015414f79caedef7d2ba624d","name":"verification() [DEV]","status":"skipped","duration":0},{"id":"63cfedde529bf87421b9227ad8216c66","name":"Applications Integration Tests › should list applications [DEV]","status":"skipped","duration":1000},{"id":"ed7da034e53d07c68e56a2c3bbea8f5c","name":"fromMapToList() [DEV]","status":"passed","duration":2},{"id":"bbf4456c8d9bdc71d24cb60051cf95c0","name":"addTestManual() [DEV]","status":"passed","duration":9},{"id":"2e86f0c3daf8bd9b1b2bd3212454174c","name":"testEPasswordsIntegration() [DEV]","status":"passed","duration":1330},{"id":"31024e1b3592fd895874eba9c19e1f3a","name":"testExcelSum() [DEV]","status":"passed","duration":91},{"id":"d2df68a3f5984162eedef6e328d9ec88","name":"polkCounty(TestInfo) [DEV]","status":"skipped","duration":0},{"id":"c0979ca00a2ed7122d18c752c0214f77","name":"t003(TestInfo) [DEV]","status":"skipped","duration":2},{"id":"245104c99d009702923bd174fa334e56","name":"Artillery Smoke Test [DEV]","status":"passed","duration":12338000},{"id":"39bbe19af70e8d0b258989da7f396249","name":"tBoxOfficeClickColumnRow(TestInfo) [DEV]","status":"skipped","duration":0},{"id":"9a9460371522acb7ae79dbdc734ea12b","name":"hardees(TestInfo) [DEV]","status":"skipped","duration":0},{"id":"a161566ca6d72d97363fbf4f848f9fd5","name":"vivitTest(TestInfo) [DEV]","status":"skipped","duration":0},{"id":"b0571ccae9697c5984bb45ce5a3118df","name":"Wizard Tests › test_job_search_sites_api - Click Job Search Sites Navigation, verify all Names and URLs against API [DEV]","status":"passed","duration":1820},{"id":"712c3d7848ded54daf91cb8401d175d0","name":"vivitCreateYmapiMapping(TestInfo) [DEV]","status":"skipped","duration":0},{"id":"a47df963e5ae98a71f42ccb0287d9915","name":"HomePage › should display the navigation panel [DEV]","status":"passed","duration":1285},{"id":"48cfcfc223a8e15cc85457fda921cf01","name":"tBoxOfficeClickRowColumn(TestInfo) [DEV]","status":"skipped","duration":0},{"id":"3d70320c1ff50cef99f461abd16993ae","name":"fromListToDataTable() [DEV]","status":"passed","duration":5},{"id":"12cef89370903fe628ce26a3ec7d696d","name":"testGetSecretKey() [DEV]","status":"passed","duration":2},{"id":"b0ee988f352576223635e6b41e70b1e4","name":"fromNumberToLetter() [DEV]","status":"passed","duration":2},{"id":"0bb1e96562d8e67cba6323f71f6f4f60","name":"assertXMLEqualFail() [DEV]","status":"skipped","duration":8},{"id":"99596515b85760e4a001ab98a73c7036","name":"Wizard Tests [DEV]","status":"passed","duration":867},{"id":"4bdbeee5d81872ccba904b086937eaeb","name":"verification() [DEV]","status":"skipped","duration":0},{"id":"11a6766eca8d048fd5eeed66b642fb5b","name":"linkedIn(TestInfo) [DEV]","status":"skipped","duration":0},{"id":"570a9360131d341e643b266a4ef53277","name":"jenkinsColors(TestInfo) [DEV]","status":"skipped","duration":0},{"id":"ff2091d4aa91947b44ab10fc035685e5","name":"jenkinsTestSendEMail(TestInfo) [DEV]","status":"skipped","duration":0},{"id":"c591695493bbd2f72162ebc8bccad583","name":"t004(TestInfo) [DEV]","status":"skipped","duration":3},{"id":"b8480371654ed6bd6408a187cc619bd2","name":"Applications Integration Tests › should delete an application [DEV]","status":"skipped","duration":1000},{"id":"55744214dd17ca1c24d87eb3d8543754","name":"google(TestInfo) [DEV]","status":"skipped","duration":0},{"id":"2dec117a2e877d7a60e9c6bb1a1ed7ff","name":"t001(TestInfo) [DEV]","status":"skipped","duration":0},{"id":"a39fc0b9e77f1c73b0cd7e82efe1872c","name":"testBoxOfficeMojo01(TestInfo) [DEV]","status":"skipped","duration":0},{"id":"ff0746a45700207b32c55830f799218b","name":"Wizard Tests [DEV]","status":"passed","duration":742},{"id":"1c5345cce0b4efd1f8922b6e1b15d665","name":"testCommandLine() [DEV]","status":"passed","duration":31},{"id":"78ed50dae29b77d6f01b06a20ee9a22f","name":"Wizard Tests › test_home - Click Home Navigation, Add Application button, then Cancel [DEV]","status":"passed","duration":3593},{"id":"d83f4a86520a2fdd04c2d063f21f25fe","name":"testAuth() [DEV]","status":"skipped","duration":1},{"id":"1b163074c385ab8c318b4bd0cc352b9b","name":"testNumbering() [DEV]","status":"passed","duration":1580},{"id":"dc29cd4826951d223076303619eaad57","name":"sharepointServiceTest() [DEV]","status":"skipped","duration":0},{"id":"7276bd54b7c39ebcfd2a7575c9e57795","name":"createClassesTest() [DEV]","status":"skipped","duration":0},{"id":"0325d604c5be94043fcd2f3050487258","name":"testConstructorWithOptionsExists() [DEV]","status":"passed","duration":10},{"id":"f142a316b674c25393d687c0c387a4d4","name":"testResponsiveDesignMultipleDevices [DEV]","status":"passed","duration":1053},{"id":"9c49eab5664a760c875cfe8333409e51","name":"emptyTest() [DEV]","status":"passed","duration":6},{"id":"dd8a4a35aaa3ad482323087f820e8e3d","name":"t00N(TestInfo) [DEV]","status":"passed","duration":2},{"id":"9c049b9d5744a145e77aad353f5c0800","name":"assertXMLEqualsFail() [DEV]","status":"skipped","duration":4},{"id":"4134ab3440688ec1262b0fb9cac0f974","name":"testMobileFontLegibility [DEV]","status":"passed","duration":1875},{"id":"10dcd8d1435f9217864304152b8fb1a1","name":"testOrientationChanges [DEV]","status":"passed","duration":4254},{"id":"3eb20cfcaf4e8b13eb8b08fcb933627b","name":"testProcesses() [DEV]","status":"passed","duration":10},{"id":"75e7b071d0f50b5bdcd618983654e9ef","name":"testCompanyEnvironmentData() [DEV]","status":"passed","duration":193},{"id":"4babdfdbe6b62e97694a27fb28b8243c","name":"fromDataTableToMap() [DEV]","status":"passed","duration":2},{"id":"03bc99ca74955ff33b264c212d7d1a0c","name":"testConstructorExists() [DEV]","status":"passed","duration":1},{"id":"d9709036a308237ea11761152c632e64","name":"mainTest() [DEV]","status":"passed","duration":1209},{"id":"2499c4b91dc88ac017b1fdac6f515f89","name":"testNavigateToGoogle(TestInfo) [DEV]","status":"skipped","duration":0},{"id":"0ee97bcd021847bcab9fa04a9fcc5438","name":"tIngore(TestInfo) [DEV]","status":"passed","duration":2},{"id":"9757ae7d4fd852d4be4f1a862ac66c83","name":"HomePage [DEV]","status":"passed","duration":866},{"id":"89547a4223ecc40de8de631badbb22bb","name":"testNavigateToGitHub(TestInfo) [DEV]","status":"skipped","duration":0},{"id":"80f2b0b19183570ea090b5a0bcf03b13","name":"testStaticGenerateMethodWithOptionsExists() [DEV]","status":"passed","duration":1},{"id":"88005b1be15a4524663545c762517a79","name":"Get All Posts Test [DEV]","status":"passed","duration":51},{"id":"60c25a41d770434b7cb2d81c9044812b","name":"testGeneratorIsNotAbstract() [DEV]","status":"passed","duration":2},{"id":"8cec3bca6dfc0ef1d567103a10acaf2f","name":"readFromXML() [DEV]","status":"skipped","duration":0},{"id":"438b39bd7406620350ad0b8c40131a6c","name":"Companies Integration Tests › should navigate to companies from home page [DEV]","status":"skipped","duration":1000},{"id":"77024bb7cd7e09a38d91e071f60c88d4","name":"testQueryAccess(TestInfo) [DEV]","status":"skipped","duration":0},{"id":"9206d2ffd5b15bd83e48928fc12e9d03","name":"testClassSetup03(TestInfo) [DEV]","status":"skipped","duration":0},{"id":"e966642ff49ea155d67b736c340aa2fe","name":"t001(TestInfo) [DEV]","status":"passed","duration":663},{"id":"e1a4d77c57e8126755458567f2e715e8","name":"testEventsEventsGet() [DEV]","status":"skipped","duration":0},{"id":"66f522c8745698eb96933e620da3c615","name":"Wizard Tests › test_contacts - Click Contacts Navigation, Add button, populate all fields, then Cancel [DEV]","status":"passed","duration":2759},{"id":"c927a074bb114b4d982f1f248540d953","name":"tBoxOffice(TestInfo) [DEV]","status":"skipped","duration":0},{"id":"c59debe1a9e2fbcdfaec0de294bc7ba0","name":"testQueryMapping(TestInfo) [DEV]","status":"skipped","duration":0},{"id":"ae30cbbea3947b9fceb36a12fbbbf5cf","name":"testFilesFolders() [DEV]","status":"passed","duration":15},{"id":"f0de15135955a200ddf5835b27d73238","name":"testMobileViewportConfiguration [DEV]","status":"passed","duration":6709},{"id":"41cd7b2c2279bc62a2fedeb9bbd70649","name":"testBoxOfficeMojo00(TestInfo) [DEV]","status":"skipped","duration":0},{"id":"e7451fb485f81e065340b7c2fc2c6b06","name":"Wizard Tests › test_clients - Click Clients Navigation, Add button, populate all fields, then Cancel [DEV]","status":"passed","duration":2662},{"id":"b855fa162c2d41b387e8d960d29dbeba","name":"Wizard Tests › test_notes - Click Notes Navigation, verify there are no notes [DEV]","status":"passed","duration":1595},{"id":"45b85b5b1fa7e9bc4a6b492b5aa2fba9","name":"testStaticGenerateMethodExists() [DEV]","status":"passed","duration":1},{"id":"76a17a3cfa2c815910af745aec9deb72","name":"testAll() [DEV]","status":"skipped","duration":0},{"id":"0f05aca8af4ac1538404abde0dcda09f","name":"createGTWNamespaceClasses() [DEV]","status":"skipped","duration":0},{"id":"26a97fc8c8d188fa59c9409555a7a7a7","name":"Home Page Should Load [DEV]","status":"passed","duration":3721},{"id":"7b9e801a08108cec176770e7bb570e6d","name":"t001(TestInfo) [DEV]","status":"skipped","duration":155},{"id":"30b3803797b1495708881e292957911d","name":"marlboro(TestInfo) [DEV]","status":"skipped","duration":0},{"id":"ce50856e872a5f5500b64cf3083197c8","name":"testMultiplePasswords() [DEV]","status":"passed","duration":5},{"id":"25eb4fe59f1acde9c26df9eda1e013b2","name":"fromMapToDataTable() [DEV]","status":"passed","duration":2},{"id":"2e5a25a82936da41b6f44d85d4a566b1","name":"jenkinsPluralsight(TestInfo) [DEV]","status":"skipped","duration":0},{"id":"fa1e9bba00ed85d8c994060ed1d10343","name":"getStatisticalTimings() [DEV]","status":"passed","duration":28},{"id":"532cc977ea0eeaf10fe015e22c5106c4","name":"jenkins(TestInfo) [DEV]","status":"skipped","duration":0},{"id":"85b993f6f407d6b3c4ed2447d0332408","name":"tBoxOfficeSearch(TestInfo) [DEV]","status":"skipped","duration":0},{"id":"11a7588d91a5269b234859e434ae48cf","name":"fromDataTableToList() [DEV]","status":"passed","duration":1},{"id":"6bd460b8bb9ff638b6a4c9f4b4bae9a1","name":"testCaching() [DEV]","status":"passed","duration":8},{"id":"e70eebf91acf197f7f696ab5c914f51d","name":"Wizard Tests [DEV]","status":"passed","duration":64},{"id":"049905a93e1f33b155175fc5bb13081c","name":"testSaEventsEventRegistrationGet() [DEV]","status":"skipped","duration":0},{"id":"8d4155050e8862d483797648ce8a93bf","name":"HomePage [DEV]","status":"passed","duration":317},{"id":"1c3f6ea350586c2c5b5c7e7c1a26d862","name":"getDatabaseTablesViewsFields() [DEV]","status":"skipped","duration":0},{"id":"f803e86a146bbd0eadabfb0934f9e44c","name":"testMobileDeviceEmulation [DEV]","status":"passed","duration":7833},{"id":"23d9846cd91f9d177ff9c327f582fe00","name":"Wizard Tests [DEV]","status":"passed","duration":3586},{"id":"c590906325ba3a4127d8fdc364d96e38","name":"marlboroEarnPoints(TestInfo) [DEV]","status":"skipped","duration":0},{"id":"3f62fa29dbc1fa1afe08e9a80bd64747","name":"Wizard Tests [DEV]","status":"passed","duration":1660},{"id":"466a9bc7cbea369a7a667ff929ca83ac","name":"assertXMLEqualsPass() [DEV]","status":"skipped","duration":1},{"id":"eb436d2649249fae87158e3aa94702e5","name":"testMobileNavigationMenu [DEV]","status":"passed","duration":3217},{"id":"b6eaa52226214e5fbb4d6a2cfa280dbf","name":"edbDrivers() [DEV]","status":"passed","duration":2},{"id":"85a7cbe06bfa2cecdfb7c22a7eccdba7","name":"testMobileFormInput [DEV]","status":"passed","duration":7013},{"id":"ae80d60fcfb46d004aa37e1e7c494bea","name":"testEventsAllSearch() [DEV]","status":"skipped","duration":0},{"id":"ff497be46dd8416ce947623fd7eb6d27","name":"testMobileImageOptimization [DEV]","status":"passed","duration":1145},{"id":"4572397b56c13deb6a606f9da86f901f","name":"should execute syncAPIMocked without errors [DEV]","status":"passed","duration":1614},{"id":"87e790ae2ba4e6b747f525e63ec405b8","name":"testMultipleViewportSizes [DEV]","status":"passed","duration":18464},{"id":"6d5c7b517d1bd2607222047cec3e2fee","name":"should execute asyncAPIMocked without errors [DEV]","status":"passed","duration":3304},{"id":"b5b4ca395a6a9f9e3ef44b15907eb1f7","name":"Wizard Tests [DEV]","status":"passed","duration":4241},{"id":"3dc0e3ac630f08f48ccd6ca1dd29c5ce","name":"Wizard Tests [DEV]","status":"passed","duration":4333},{"id":"10a8921eba6c895b1a65fb5278cd5316","name":"testGetJpsProcesses() [DEV]","status":"passed","duration":619},{"id":"b529692432a841658937d29fddfc0e62","name":"testMobileTouchInteractions [DEV]","status":"passed","duration":4775},{"id":"c485692e0e3704c58f6b4c9c5103e143","name":"Get Posts API Test [DEV]","status":"passed","duration":87},{"id":"fd24cabee033d291887090396e6300ea","name":"should execute asyncAPIHandled without errors [DEV]","status":"passed","duration":6403},{"id":"531ed562724777984986b1b83dac5634","name":"testXLS() [DEV]","status":"passed","duration":1534},{"id":"d47a4c34cecaec99b91372eb1b4ba18d","name":"addTestCucumberScenario() [DEV]","status":"passed","duration":13},{"id":"fd0d7b1afd105a003b42e4a904c9af98","name":"Wizard Tests [DEV]","status":"passed","duration":2053},{"id":"a3d4ac0f392188ac109b31f260f13c63","name":"Wizard Tests › test_job_search_sites_db - Click Job Search Sites Navigation, verify all Names and URLs against database [DEV]","status":"passed","duration":1451},{"id":"872173b8569c7bb90d6a578044307efa","name":"Create Post Test [DEV]","status":"passed","duration":54},{"id":"447e650d66a1502148609ab965b25a37","name":"Home Page Should Display Navigation Panel [DEV]","status":"passed","duration":3211},{"id":"c9c2e41cec3ab87dc6d2bdf632715d7c","name":"should execute all example functions in sequence [DEV]","status":"passed","duration":4954},{"id":"4ad6bbae9f2eb14f6e254e17f25a20d2","name":"should execute syncAPIHandled without errors [DEV]","status":"passed","duration":499},{"id":"0858f911d3b0393af2614ca758c21b8a","name":"testMobilePageLoadPerformance [DEV]","status":"passed","duration":7090}],"flakyTests":[],"retryTests":[],"meta":{"reportId":"d83fa34d-07bb-40ab-a936-ef020de63398","singleFile":false,"withTestResultsLinks":true},"pullRequestHref":"","jobHref":"https://github.com/CScharer/full-stack-qa/actions/runs/26709379106"}